boardgen/__init__.py
boardgen/__main__.py
boardgen/cli.py
boardgen/core/__init__.py
boardgen/core/cache.py
boardgen/core/core.py
boardgen/core/getters.py
boardgen/draw_util.py
boardgen/mixins.py
boardgen/models/__init__.py
boardgen/models/board.py
boardgen/models/enums.py
boardgen/models/flash_region.py
boardgen/models/pcb.py
boardgen/models/role.py
boardgen/models/template.py
boardgen/readme/__init__.py
boardgen/readme/parts.py
boardgen/readme/writer.py
boardgen/res/boards/README.md
boardgen/res/flash.json
boardgen/res/presets.json
boardgen/res/roles.json
boardgen/res/shapes/chip.json
boardgen/res/shapes/esp01m.json
boardgen/res/shapes/label_line_down.json
boardgen/res/shapes/label_line_up.json
boardgen/res/shapes/osc.json
boardgen/res/shapes/pad.json
boardgen/res/shapes/pad_10x25.json
boardgen/res/shapes/pin_horz_cast_hole.json
boardgen/res/shapes/pin_horz_cast_nohole.json
boardgen/res/shapes/pin_vert_cast_hole.json
boardgen/res/shapes/pin_vert_cast_nohole.json
boardgen/res/shapes/r_labels_horz.json
boardgen/res/shapes/r_pins_horz.json
boardgen/res/shapes/r_pins_vert.json
boardgen/res/shapes/test_pad_1mm.json
boardgen/res/templates/esp01m-14.json
boardgen/res/templates/esp01m-18.json
boardgen/res/templates/esp12e-21.json
boardgen/res/templates/esp12e-22.json
boardgen/res/templates/esp12s.json
boardgen/res/templates/gui-design-test.json
boardgen/res/templates/pcb-black.json
boardgen/res/templates/pcb-blue-light.json
boardgen/res/templates/pcb-white.json
boardgen/res/templates/rf-type1.json
boardgen/shapes/__init__.py
boardgen/shapes/base.py
boardgen/shapes/circle.py
boardgen/shapes/fill_style.py
boardgen/shapes/group.py
boardgen/shapes/label/__init__.py
boardgen/shapes/label/block.py
boardgen/shapes/label/io_line.py
boardgen/shapes/label/label.py
boardgen/shapes/rect.py
boardgen/shapes/text.py
boardgen/utils.py
boardgen/variant/__init__.py
boardgen/variant/features.py
boardgen/variant/parts.py
boardgen/variant/section.py
boardgen/variant/writer.py
boardgen-0.12.0.dist-info/METADATA
boardgen-0.12.0.dist-info/WHEEL
boardgen-0.12.0.dist-info/entry_points.txt
boardgen-0.12.0.dist-info/licenses/LICENSE
boardgen-0.12.0.dist-info/RECORD
