Metadata-Version: 2.4
Name: boardgen
Version: 0.12.0
Summary: Board pinout diagram generator (with ltchiptool plugin GUI editor)
License: MIT
License-File: LICENSE
Author: Kuba Szczodrzyński
Author-email: kuba@szczodrzynski.pl
Requires-Python: >=3.10,<4.0
Classifier: License :: OSI Approved :: MIT License
Classifier: Programming Language :: Python :: 3
Classifier: Programming Language :: Python :: 3.10
Classifier: Programming Language :: Python :: 3.11
Classifier: Programming Language :: Python :: 3.12
Classifier: Programming Language :: Python :: 3.13
Classifier: Programming Language :: Python :: 3.14
Requires-Dist: click (>=8.1.3,<9.0.0)
Requires-Dist: devtools (>=0.8.0,<0.9.0)
Requires-Dist: markdown2 (>=2.4.10,<3.0.0)
Requires-Dist: natsort (>=8.2.0,<9.0.0)
Requires-Dist: pydantic (>=2.7.1,<3.0.0)
Requires-Dist: svgwrite (>=1.4.2,<2.0.0)
